{
  "display": {
    "icon": {
      "id": "compressedblocks:c5_tnt"
    },
    "title": "TNT Addiction: VI",
    "description": "§5Compress 9x Quintuple Compressed §2TNT§5 into Sextuple Compressed §2TNT",
    "frame": "challenge",
    "show_toast": true,
    "announce_to_chat": true,
    "hidden": false
  },
  "parent": "compressedblocks:addiction/c4_tnt_edition",
  "criteria": {
    "get_c5_tnt_edition": {
      "trigger": "minecraft:inventory_changed",
      "conditions": {
        "items": [
          {
            "items": [
              "compressedblocks:c5_tnt"
            ]
          }
        ]
      }
    }
  },
  "requirements": [
    [
      "get_c5_tnt_edition"
    ]
  ],
  "rewards": {
    "experience": 3000
  },
  "sends_telemetry_event": true
}
