{
  "display": {
    "icon": {
      "id": "compressedblocks:c7_iron_block"
    },
    "title": "Iron Addiction: VIII",
    "description": "§5Compress 9x Septuple Compressed §2Iron Block§5 into Octuple Compressed §2Iron Block",
    "frame": "challenge",
    "show_toast": true,
    "announce_to_chat": true,
    "hidden": false
  },
  "parent": "compressedblocks:addiction/c6_iron_edition",
  "criteria": {
    "get_c7_iron_edition": {
      "trigger": "minecraft:inventory_changed",
      "conditions": {
        "items": [
          {
            "items": [
              "compressedblocks:c7_iron_block"
            ]
          }
        ]
      }
    }
  },
  "requirements": [
    [
      "get_c7_iron_edition"
    ]
  ],
  "rewards": {
    "experience": 5000
  },
  "sends_telemetry_event": true
}
